{
  "type": "Feature",
  "properties": {
    "millsfield:count_images": 16,
    "millsfield:count_objects": 16,
    "sfomuseum:category": "Insignia",
    "sfomuseum:collection": "Aviation Museum",
    "sfomuseum:placetype": "subcategory",
    "sfomuseum:subcategory": "Uniform Wing(s), Ground Crew",
    "wof:name": "Uniform Wing(s), Ground Crew",
    "wof:placetype": "custom",
    "wof:placetype_alt": [
      "subcategory"
    ]
  },
  "geometry": {"coordinates":[-122.386155,37.616357],"type":"Point"}
}
