{
  "type": "Feature",
  "properties": {
    "iso:country":"US",
    "sfomuseum:category":"Philately",
    "sfomuseum:collection":"Aviation Archive",
    "sfomuseum:placetype":"subcategory",
    "sfomuseum:subcategory":"Airmail Flight Cover",
    "wof:name":"Airmail Flight Cover",
    "wof:placetype":"classification"
},
  "geometry": {"coordinates":[-122.386155,37.616357],"type":"Point"}
}