{
  "type": "Feature",
  "properties": {
    "millsfield:count_images": 3884,
    "millsfield:count_objects": 2458,
    "sfomuseum:category": "Promotional, Museum",
    "sfomuseum:collection": "Aviation Museum",
    "sfomuseum:placetype": "category",
    "wof:name": "Promotional, Museum",
    "wof:placetype": "custom",
    "wof:placetype_alt": [
      "category"
    ]
  },
  "geometry": {"coordinates":[-122.386155,37.616357],"type":"Point"}
}
